pynsted/__init__.py
pynsted/py.typed
pynsted-1.0.8.dist-info/METADATA
pynsted-1.0.8.dist-info/WHEEL
pynsted-1.0.8.dist-info/RECORD
