Metadata-Version: 2.1
Name: pynsted
Version: 1.0.8
Summary: Add a method to dictionaries to get nested values
Home-page: https://github.com/pragmatic-fi/pynsted
Keywords: dictionary,nested
Author: The Pragmatic Solutions
Author-email: contact@thepragmatic.fi
Requires-Python: >=3.11,<3.13
Classifier: Development Status :: 4 - Beta
Classifier: Intended Audience :: Developers
Classifier: License :: OSI Approved :: BSD License
Classifier: Programming Language :: Python :: 3
Classifier: Programming Language :: Python :: 3.11
Classifier: Programming Language :: Python :: 3.12
Project-URL: Repository, https://github.com/pragmatic-fi/pynsted.git
